{"https://list.worldfloraonline.org/wfo-4000016965-2025-12": {"http://www.w3.org/1999/02/22-rdf-syntax-ns#type": [{"type": "uri", "value": "https://list.worldfloraonline.org/terms/TaxonConcept"}], "https://list.worldfloraonline.org/terms/classification": [{"type": "uri", "value": "https://list.worldfloraonline.org/2025-12"}], "http://purl.org/dc/terms/replaces": [{"type": "uri", "value": "https://list.worldfloraonline.org/wfo-4000016965-2025-06"}], "https://list.worldfloraonline.org/terms/hasName": [{"type": "uri", "value": "https://list.worldfloraonline.org/wfo-4000016965"}], "http://purl.org/dc/terms/isPartOf": [{"type": "uri", "value": "https://list.worldfloraonline.org/wfo-4100000017-2025-12"}], "http://purl.org/dc/terms/hasPart": [{"type": "uri", "value": "https://list.worldfloraonline.org/wfo-0000715812-2025-12"}, {"type": "uri", "value": "https://list.worldfloraonline.org/wfo-0000715815-2025-12"}, {"type": "uri", "value": "https://list.worldfloraonline.org/wfo-0000715816-2025-12"}, {"type": "uri", "value": "https://list.worldfloraonline.org/wfo-0000715818-2025-12"}, {"type": "uri", "value": "https://list.worldfloraonline.org/wfo-0000715819-2025-12"}, {"type": "uri", "value": "https://list.worldfloraonline.org/wfo-0000715820-2025-12"}, {"type": "uri", "value": "https://list.worldfloraonline.org/wfo-0000715825-2025-12"}, {"type": "uri", "value": "https://list.worldfloraonline.org/wfo-0000715826-2025-12"}, {"type": "uri", "value": "https://list.worldfloraonline.org/wfo-0000715830-2025-12"}, {"type": "uri", "value": "https://list.worldfloraonline.org/wfo-0000715833-2025-12"}, {"type": "uri", "value": "https://list.worldfloraonline.org/wfo-0000715835-2025-12"}, {"type": "uri", "value": "https://list.worldfloraonline.org/wfo-0000715836-2025-12"}, {"type": "uri", "value": "https://list.worldfloraonline.org/wfo-0000715840-2025-12"}, {"type": "uri", "value": "https://list.worldfloraonline.org/wfo-0000715841-2025-12"}, {"type": "uri", "value": "https://list.worldfloraonline.org/wfo-0000715842-2025-12"}, {"type": "uri", "value": "https://list.worldfloraonline.org/wfo-0000715845-2025-12"}, {"type": "uri", "value": "https://list.worldfloraonline.org/wfo-0000749538-2025-12"}, {"type": "uri", "value": "https://list.worldfloraonline.org/wfo-0000715850-2025-12"}, {"type": "uri", "value": "https://list.worldfloraonline.org/wfo-0000715852-2025-12"}, {"type": "uri", "value": "https://list.worldfloraonline.org/wfo-0000715854-2025-12"}, {"type": "uri", "value": "https://list.worldfloraonline.org/wfo-0000715855-2025-12"}, {"type": "uri", "value": "https://list.worldfloraonline.org/wfo-0001135002-2025-12"}, {"type": "uri", "value": "https://list.worldfloraonline.org/wfo-0000715856-2025-12"}, {"type": "uri", "value": "https://list.worldfloraonline.org/wfo-0000715860-2025-12"}, {"type": "uri", "value": "https://list.worldfloraonline.org/wfo-0000715861-2025-12"}, {"type": "uri", "value": "https://list.worldfloraonline.org/wfo-0000715863-2025-12"}, {"type": "uri", "value": "https://list.worldfloraonline.org/wfo-0000715865-2025-12"}, {"type": "uri", "value": "https://list.worldfloraonline.org/wfo-0000715867-2025-12"}], "http://purl.org/dc/terms/hasSynonym": [{"type": "uri", "value": "https://list.worldfloraonline.org/wfo-4000002342"}, {"type": "uri", "value": "https://list.worldfloraonline.org/wfo-4000002663"}, {"type": "uri", "value": "https://list.worldfloraonline.org/wfo-4000012404"}, {"type": "uri", "value": "https://list.worldfloraonline.org/wfo-4000027469"}]}, "https://list.worldfloraonline.org/wfo-4000016965": {"http://www.w3.org/1999/02/22-rdf-syntax-ns#type": [{"type": "uri", "value": "https://list.worldfloraonline.org/terms/TaxonName"}], "https://list.worldfloraonline.org/terms/rank": [{"type": "uri", "value": "https://list.worldfloraonline.org/terms/genus"}], "https://list.worldfloraonline.org/terms/fullName": [{"type": "literal", "value": "Harpullia Roxb."}], "https://list.worldfloraonline.org/terms/authorship": [{"type": "literal", "value": "Roxb."}], "http://purl.org/dc/terms/creator": [{"type": "literal", "value": "Roxb."}], "https://list.worldfloraonline.org/terms/publicationCitation": [{"type": "literal", "value": "Fl. Ind. 2: 441 (1824)"}], "https://list.worldfloraonline.org/terms/acceptedNameFor": [{"type": "uri", "value": "https://list.worldfloraonline.org/wfo-4000016965-2018-07"}, {"type": "uri", "value": "https://list.worldfloraonline.org/wfo-4000016965-2019-03"}, {"type": "uri", "value": "https://list.worldfloraonline.org/wfo-4000016965-2019-05"}, {"type": "uri", "value": "https://list.worldfloraonline.org/wfo-4000016965-2021-12"}, {"type": "uri", "value": "https://list.worldfloraonline.org/wfo-4000016965-2022-06"}, {"type": "uri", "value": "https://list.worldfloraonline.org/wfo-4000016965-2022-12"}, {"type": "uri", "value": "https://list.worldfloraonline.org/wfo-4000016965-2023-06"}, {"type": "uri", "value": "https://list.worldfloraonline.org/wfo-4000016965-2023-12"}, {"type": "uri", "value": "https://list.worldfloraonline.org/wfo-4000016965-2024-06"}, {"type": "uri", "value": "https://list.worldfloraonline.org/wfo-4000016965-2024-12"}, {"type": "uri", "value": "https://list.worldfloraonline.org/wfo-4000016965-2025-06"}, {"type": "uri", "value": "https://list.worldfloraonline.org/wfo-4000016965-2025-12"}], "https://list.worldfloraonline.org/terms/currentPreferredUsage": [{"type": "uri", "value": "https://list.worldfloraonline.org/wfo-4000016965-2025-12"}], "http://purl.org/dc/terms/references": [{"type": "uri", "value": "https://www.biodiversitylibrary.org/page/34213910"}, {"type": "uri", "value": "http://www.wikidata.org/entity/Q748967"}, {"type": "uri", "value": "https://www.ipni.org/n/326337-2"}, {"type": "uri", "value": "http://www.theplantlist.org/browse/A/Sapindaceae/Harpullia/"}, {"type": "uri", "value": "http://www.theplantlist.org/1.1/browse/A/Sapindaceae/Harpullia/"}]}, "https://www.biodiversitylibrary.org/page/34213910": {"http://purl.org/dc/terms/title": [{"type": "literal", "value": "Fl. Ind. (Carey & Wallich ed.) 2: 441. 1824 [Mar-Jun ? 1824] "}], "http://purl.org/dc/terms/type": [{"type": "literal", "value": "literature"}], "http://purl.org/dc/terms/description": [{"type": "literal", "value": "BHL link from IPNI metadata."}], "http://ogp.me/ns#image": [{"type": "uri", "value": "https://www.biodiversitylibrary.org/pagethumb/34213910"}]}, "http://www.wikidata.org/entity/Q748967": {"http://purl.org/dc/terms/title": [{"type": "literal", "value": "William Roxburgh (1751-1815)"}], "http://purl.org/dc/terms/type": [{"type": "literal", "value": "person"}], "http://purl.org/dc/terms/description": [{"type": "literal", "value": "Based on occurrence of standard abbreviation 'Roxb.' in the authors string."}], "http://ogp.me/ns#image": [{"type": "uri", "value": "https://upload.wikimedia.org/wikipedia/commons/thumb/9/95/William_Roxburgh.jpg/200px-William_Roxburgh.jpg"}]}, "https://www.ipni.org/n/326337-2": {"http://purl.org/dc/terms/title": [{"type": "literal", "value": "IPNI record: 326337-2"}], "http://purl.org/dc/terms/type": [{"type": "literal", "value": "database"}]}, "http://www.theplantlist.org/browse/A/Sapindaceae/Harpullia/": {"http://purl.org/dc/terms/title": [{"type": "literal", "value": "The Plant List version 1.0, record: Sapindaceae Harpullia"}], "http://purl.org/dc/terms/type": [{"type": "literal", "value": "database"}]}, "http://www.theplantlist.org/1.1/browse/A/Sapindaceae/Harpullia/": {"http://purl.org/dc/terms/title": [{"type": "literal", "value": "The Plant List version 1.1, record: Sapindaceae Harpullia"}], "http://purl.org/dc/terms/type": [{"type": "literal", "value": "database"}]}}