{"https://list.worldfloraonline.org/wfo-4000003062-2025-12": {"http://www.w3.org/1999/02/22-rdf-syntax-ns#type": [{"type": "uri", "value": "https://list.worldfloraonline.org/terms/TaxonConcept"}], "https://list.worldfloraonline.org/terms/classification": [{"type": "uri", "value": "https://list.worldfloraonline.org/2025-12"}], "http://purl.org/dc/terms/replaces": [{"type": "uri", "value": "https://list.worldfloraonline.org/wfo-4000003062-2025-06"}], "https://list.worldfloraonline.org/terms/hasName": [{"type": "uri", "value": "https://list.worldfloraonline.org/wfo-4000003062"}], "http://purl.org/dc/terms/isPartOf": [{"type": "uri", "value": "https://list.worldfloraonline.org/wfo-4100006195-2025-12"}], "http://purl.org/dc/terms/hasPart": [{"type": "uri", "value": "https://list.worldfloraonline.org/wfo-0000547500-2025-12"}, {"type": "uri", "value": "https://list.worldfloraonline.org/wfo-0000547501-2025-12"}, {"type": "uri", "value": "https://list.worldfloraonline.org/wfo-0000547502-2025-12"}, {"type": "uri", "value": "https://list.worldfloraonline.org/wfo-0001339828-2025-12"}, {"type": "uri", "value": "https://list.worldfloraonline.org/wfo-1000020487-2025-12"}, {"type": "uri", "value": "https://list.worldfloraonline.org/wfo-0000547504-2025-12"}, {"type": "uri", "value": "https://list.worldfloraonline.org/wfo-0000547505-2025-12"}, {"type": "uri", "value": "https://list.worldfloraonline.org/wfo-0001347617-2025-12"}, {"type": "uri", "value": "https://list.worldfloraonline.org/wfo-0001339845-2025-12"}, {"type": "uri", "value": "https://list.worldfloraonline.org/wfo-1000061284-2025-12"}, {"type": "uri", "value": "https://list.worldfloraonline.org/wfo-0000547509-2025-12"}, {"type": "uri", "value": "https://list.worldfloraonline.org/wfo-0000547514-2025-12"}, {"type": "uri", "value": "https://list.worldfloraonline.org/wfo-0000547515-2025-12"}, {"type": "uri", "value": "https://list.worldfloraonline.org/wfo-0000547521-2025-12"}, {"type": "uri", "value": "https://list.worldfloraonline.org/wfo-1000061285-2025-12"}, {"type": "uri", "value": "https://list.worldfloraonline.org/wfo-0000547528-2025-12"}, {"type": "uri", "value": "https://list.worldfloraonline.org/wfo-0000547531-2025-12"}, {"type": "uri", "value": "https://list.worldfloraonline.org/wfo-0000547532-2025-12"}, {"type": "uri", "value": "https://list.worldfloraonline.org/wfo-0000547533-2025-12"}, {"type": "uri", "value": "https://list.worldfloraonline.org/wfo-0000547534-2025-12"}, {"type": "uri", "value": "https://list.worldfloraonline.org/wfo-0000547536-2025-12"}, {"type": "uri", "value": "https://list.worldfloraonline.org/wfo-0000547541-2025-12"}, {"type": "uri", "value": "https://list.worldfloraonline.org/wfo-0000547542-2025-12"}, {"type": "uri", "value": "https://list.worldfloraonline.org/wfo-1000020488-2025-12"}, {"type": "uri", "value": "https://list.worldfloraonline.org/wfo-0001318069-2025-12"}, {"type": "uri", "value": "https://list.worldfloraonline.org/wfo-0000547544-2025-12"}, {"type": "uri", "value": "https://list.worldfloraonline.org/wfo-0000547548-2025-12"}, {"type": "uri", "value": "https://list.worldfloraonline.org/wfo-0001339846-2025-12"}, {"type": "uri", "value": "https://list.worldfloraonline.org/wfo-0000547550-2025-12"}, {"type": "uri", "value": "https://list.worldfloraonline.org/wfo-0000547552-2025-12"}, {"type": "uri", "value": "https://list.worldfloraonline.org/wfo-0000547553-2025-12"}, {"type": "uri", "value": "https://list.worldfloraonline.org/wfo-0000547554-2025-12"}, {"type": "uri", "value": "https://list.worldfloraonline.org/wfo-0000547555-2025-12"}, {"type": "uri", "value": "https://list.worldfloraonline.org/wfo-0000547556-2025-12"}, {"type": "uri", "value": "https://list.worldfloraonline.org/wfo-0000547558-2025-12"}, {"type": "uri", "value": "https://list.worldfloraonline.org/wfo-0000547560-2025-12"}, {"type": "uri", "value": "https://list.worldfloraonline.org/wfo-0000547562-2025-12"}, {"type": "uri", "value": "https://list.worldfloraonline.org/wfo-0000547566-2025-12"}, {"type": "uri", "value": "https://list.worldfloraonline.org/wfo-0000547567-2025-12"}, {"type": "uri", "value": "https://list.worldfloraonline.org/wfo-0000547568-2025-12"}, {"type": "uri", "value": "https://list.worldfloraonline.org/wfo-0000547570-2025-12"}, {"type": "uri", "value": "https://list.worldfloraonline.org/wfo-0001425508-2025-12"}, {"type": "uri", "value": "https://list.worldfloraonline.org/wfo-0000547574-2025-12"}, {"type": "uri", "value": "https://list.worldfloraonline.org/wfo-0000547575-2025-12"}, {"type": "uri", "value": "https://list.worldfloraonline.org/wfo-0001346973-2025-12"}, {"type": "uri", "value": "https://list.worldfloraonline.org/wfo-0000547577-2025-12"}, {"type": "uri", "value": "https://list.worldfloraonline.org/wfo-0000547578-2025-12"}, {"type": "uri", "value": "https://list.worldfloraonline.org/wfo-0000547580-2025-12"}, {"type": "uri", "value": "https://list.worldfloraonline.org/wfo-1000020489-2025-12"}, {"type": "uri", "value": "https://list.worldfloraonline.org/wfo-0000547581-2025-12"}, {"type": "uri", "value": "https://list.worldfloraonline.org/wfo-0000547584-2025-12"}, {"type": "uri", "value": "https://list.worldfloraonline.org/wfo-0000547586-2025-12"}, {"type": "uri", "value": "https://list.worldfloraonline.org/wfo-1000020490-2025-12"}, {"type": "uri", "value": "https://list.worldfloraonline.org/wfo-0000547590-2025-12"}, {"type": "uri", "value": "https://list.worldfloraonline.org/wfo-0000547591-2025-12"}, {"type": "uri", "value": "https://list.worldfloraonline.org/wfo-1000057802-2025-12"}, {"type": "uri", "value": "https://list.worldfloraonline.org/wfo-0000547595-2025-12"}, {"type": "uri", "value": "https://list.worldfloraonline.org/wfo-0000547596-2025-12"}, {"type": "uri", "value": "https://list.worldfloraonline.org/wfo-0000547601-2025-12"}, {"type": "uri", "value": "https://list.worldfloraonline.org/wfo-0000547603-2025-12"}, {"type": "uri", "value": "https://list.worldfloraonline.org/wfo-0000547604-2025-12"}, {"type": "uri", "value": "https://list.worldfloraonline.org/wfo-0000547608-2025-12"}, {"type": "uri", "value": "https://list.worldfloraonline.org/wfo-0001318304-2025-12"}, {"type": "uri", "value": "https://list.worldfloraonline.org/wfo-0000547610-2025-12"}, {"type": "uri", "value": "https://list.worldfloraonline.org/wfo-0000547611-2025-12"}, {"type": "uri", "value": "https://list.worldfloraonline.org/wfo-0000547612-2025-12"}, {"type": "uri", "value": "https://list.worldfloraonline.org/wfo-0000547613-2025-12"}, {"type": "uri", "value": "https://list.worldfloraonline.org/wfo-0000547614-2025-12"}, {"type": "uri", "value": "https://list.worldfloraonline.org/wfo-0000547615-2025-12"}, {"type": "uri", "value": "https://list.worldfloraonline.org/wfo-0000547617-2025-12"}, {"type": "uri", "value": "https://list.worldfloraonline.org/wfo-0000547619-2025-12"}, {"type": "uri", "value": "https://list.worldfloraonline.org/wfo-0000547621-2025-12"}, {"type": "uri", "value": "https://list.worldfloraonline.org/wfo-0000547622-2025-12"}, {"type": "uri", "value": "https://list.worldfloraonline.org/wfo-0000547628-2025-12"}, {"type": "uri", "value": "https://list.worldfloraonline.org/wfo-0000547630-2025-12"}, {"type": "uri", "value": "https://list.worldfloraonline.org/wfo-0000547631-2025-12"}, {"type": "uri", "value": "https://list.worldfloraonline.org/wfo-0000547632-2025-12"}, {"type": "uri", "value": "https://list.worldfloraonline.org/wfo-0000547633-2025-12"}, {"type": "uri", "value": "https://list.worldfloraonline.org/wfo-0000547637-2025-12"}, {"type": "uri", "value": "https://list.worldfloraonline.org/wfo-0000547639-2025-12"}, {"type": "uri", "value": "https://list.worldfloraonline.org/wfo-0000547640-2025-12"}, {"type": "uri", "value": "https://list.worldfloraonline.org/wfo-0000547644-2025-12"}, {"type": "uri", "value": "https://list.worldfloraonline.org/wfo-0000547645-2025-12"}, {"type": "uri", "value": "https://list.worldfloraonline.org/wfo-0000547646-2025-12"}, {"type": "uri", "value": "https://list.worldfloraonline.org/wfo-0000547647-2025-12"}, {"type": "uri", "value": "https://list.worldfloraonline.org/wfo-0000547650-2025-12"}, {"type": "uri", "value": "https://list.worldfloraonline.org/wfo-0000547655-2025-12"}, {"type": "uri", "value": "https://list.worldfloraonline.org/wfo-0000547656-2025-12"}, {"type": "uri", "value": "https://list.worldfloraonline.org/wfo-0000547657-2025-12"}, {"type": "uri", "value": "https://list.worldfloraonline.org/wfo-0001336437-2025-12"}, {"type": "uri", "value": "https://list.worldfloraonline.org/wfo-0000547658-2025-12"}, {"type": "uri", "value": "https://list.worldfloraonline.org/wfo-0000547663-2025-12"}, {"type": "uri", "value": "https://list.worldfloraonline.org/wfo-0000547669-2025-12"}, {"type": "uri", "value": "https://list.worldfloraonline.org/wfo-0000547670-2025-12"}, {"type": "uri", "value": "https://list.worldfloraonline.org/wfo-0000547673-2025-12"}, {"type": "uri", "value": "https://list.worldfloraonline.org/wfo-0000547674-2025-12"}, {"type": "uri", "value": "https://list.worldfloraonline.org/wfo-0000547676-2025-12"}, {"type": "uri", "value": "https://list.worldfloraonline.org/wfo-1000061298-2025-12"}, {"type": "uri", "value": "https://list.worldfloraonline.org/wfo-0000547678-2025-12"}, {"type": "uri", "value": "https://list.worldfloraonline.org/wfo-0000547679-2025-12"}, {"type": "uri", "value": "https://list.worldfloraonline.org/wfo-0000547680-2025-12"}, {"type": "uri", "value": "https://list.worldfloraonline.org/wfo-0000547681-2025-12"}, {"type": "uri", "value": "https://list.worldfloraonline.org/wfo-0000547687-2025-12"}, {"type": "uri", "value": "https://list.worldfloraonline.org/wfo-0000547688-2025-12"}, {"type": "uri", "value": "https://list.worldfloraonline.org/wfo-0000547689-2025-12"}, {"type": "uri", "value": "https://list.worldfloraonline.org/wfo-0000547690-2025-12"}, {"type": "uri", "value": "https://list.worldfloraonline.org/wfo-0000547693-2025-12"}, {"type": "uri", "value": "https://list.worldfloraonline.org/wfo-0000547695-2025-12"}, {"type": "uri", "value": "https://list.worldfloraonline.org/wfo-0000547697-2025-12"}, {"type": "uri", "value": "https://list.worldfloraonline.org/wfo-0000547698-2025-12"}, {"type": "uri", "value": "https://list.worldfloraonline.org/wfo-0000547699-2025-12"}, {"type": "uri", "value": "https://list.worldfloraonline.org/wfo-0000547702-2025-12"}, {"type": "uri", "value": "https://list.worldfloraonline.org/wfo-0000547703-2025-12"}, {"type": "uri", "value": "https://list.worldfloraonline.org/wfo-0000547706-2025-12"}, {"type": "uri", "value": "https://list.worldfloraonline.org/wfo-1000055394-2025-12"}, {"type": "uri", "value": "https://list.worldfloraonline.org/wfo-0000547711-2025-12"}, {"type": "uri", "value": "https://list.worldfloraonline.org/wfo-0000547712-2025-12"}, {"type": "uri", "value": "https://list.worldfloraonline.org/wfo-0000547713-2025-12"}, {"type": "uri", "value": "https://list.worldfloraonline.org/wfo-0000547714-2025-12"}, {"type": "uri", "value": "https://list.worldfloraonline.org/wfo-0000547718-2025-12"}, {"type": "uri", "value": "https://list.worldfloraonline.org/wfo-0000547721-2025-12"}, {"type": "uri", "value": "https://list.worldfloraonline.org/wfo-0000547722-2025-12"}, {"type": "uri", "value": "https://list.worldfloraonline.org/wfo-0000547723-2025-12"}, {"type": "uri", "value": "https://list.worldfloraonline.org/wfo-0000547724-2025-12"}, {"type": "uri", "value": "https://list.worldfloraonline.org/wfo-0000547727-2025-12"}, {"type": "uri", "value": "https://list.worldfloraonline.org/wfo-0000547728-2025-12"}, {"type": "uri", "value": "https://list.worldfloraonline.org/wfo-0000547729-2025-12"}, {"type": "uri", "value": "https://list.worldfloraonline.org/wfo-0000547731-2025-12"}, {"type": "uri", "value": "https://list.worldfloraonline.org/wfo-0000547732-2025-12"}, {"type": "uri", "value": "https://list.worldfloraonline.org/wfo-0000547734-2025-12"}, {"type": "uri", "value": "https://list.worldfloraonline.org/wfo-0000547740-2025-12"}, {"type": "uri", "value": "https://list.worldfloraonline.org/wfo-0000547741-2025-12"}, {"type": "uri", "value": "https://list.worldfloraonline.org/wfo-0000547742-2025-12"}, {"type": "uri", "value": "https://list.worldfloraonline.org/wfo-0000547743-2025-12"}, {"type": "uri", "value": "https://list.worldfloraonline.org/wfo-0000547744-2025-12"}, {"type": "uri", "value": "https://list.worldfloraonline.org/wfo-0000547745-2025-12"}, {"type": "uri", "value": "https://list.worldfloraonline.org/wfo-0000547749-2025-12"}, {"type": "uri", "value": "https://list.worldfloraonline.org/wfo-0000547754-2025-12"}, {"type": "uri", "value": "https://list.worldfloraonline.org/wfo-0000547757-2025-12"}, {"type": "uri", "value": "https://list.worldfloraonline.org/wfo-0000547761-2025-12"}, {"type": "uri", "value": "https://list.worldfloraonline.org/wfo-0000547762-2025-12"}, {"type": "uri", "value": "https://list.worldfloraonline.org/wfo-0000547768-2025-12"}, {"type": "uri", "value": "https://list.worldfloraonline.org/wfo-0000508416-2025-12"}, {"type": "uri", "value": "https://list.worldfloraonline.org/wfo-0000547770-2025-12"}, {"type": "uri", "value": "https://list.worldfloraonline.org/wfo-0000547771-2025-12"}, {"type": "uri", "value": "https://list.worldfloraonline.org/wfo-0000547772-2025-12"}, {"type": "uri", "value": "https://list.worldfloraonline.org/wfo-0000547776-2025-12"}, {"type": "uri", "value": "https://list.worldfloraonline.org/wfo-0000547782-2025-12"}, {"type": "uri", "value": "https://list.worldfloraonline.org/wfo-0001247971-2025-12"}, {"type": "uri", "value": "https://list.worldfloraonline.org/wfo-1000061291-2025-12"}, {"type": "uri", "value": "https://list.worldfloraonline.org/wfo-0000547785-2025-12"}, {"type": "uri", "value": "https://list.worldfloraonline.org/wfo-0000547787-2025-12"}, {"type": "uri", "value": "https://list.worldfloraonline.org/wfo-1000070392-2025-12"}, {"type": "uri", "value": "https://list.worldfloraonline.org/wfo-0000547788-2025-12"}, {"type": "uri", "value": "https://list.worldfloraonline.org/wfo-0000547792-2025-12"}, {"type": "uri", "value": "https://list.worldfloraonline.org/wfo-0000547793-2025-12"}, {"type": "uri", "value": "https://list.worldfloraonline.org/wfo-0000547794-2025-12"}, {"type": "uri", "value": "https://list.worldfloraonline.org/wfo-0000547798-2025-12"}, {"type": "uri", "value": "https://list.worldfloraonline.org/wfo-0000547799-2025-12"}, {"type": "uri", "value": "https://list.worldfloraonline.org/wfo-0000547800-2025-12"}, {"type": "uri", "value": "https://list.worldfloraonline.org/wfo-0000547802-2025-12"}, {"type": "uri", "value": "https://list.worldfloraonline.org/wfo-0000547803-2025-12"}, {"type": "uri", "value": "https://list.worldfloraonline.org/wfo-0000547804-2025-12"}, {"type": "uri", "value": "https://list.worldfloraonline.org/wfo-0000547805-2025-12"}, {"type": "uri", "value": "https://list.worldfloraonline.org/wfo-1000055592-2025-12"}, {"type": "uri", "value": "https://list.worldfloraonline.org/wfo-0000547808-2025-12"}, {"type": "uri", "value": "https://list.worldfloraonline.org/wfo-0000547809-2025-12"}, {"type": "uri", "value": "https://list.worldfloraonline.org/wfo-0001339847-2025-12"}, {"type": "uri", "value": "https://list.worldfloraonline.org/wfo-0000547815-2025-12"}, {"type": "uri", "value": "https://list.worldfloraonline.org/wfo-0000547816-2025-12"}, {"type": "uri", "value": "https://list.worldfloraonline.org/wfo-0000547817-2025-12"}, {"type": "uri", "value": "https://list.worldfloraonline.org/wfo-0000547819-2025-12"}, {"type": "uri", "value": "https://list.worldfloraonline.org/wfo-0000547820-2025-12"}, {"type": "uri", "value": "https://list.worldfloraonline.org/wfo-0000547824-2025-12"}, {"type": "uri", "value": "https://list.worldfloraonline.org/wfo-1000061272-2025-12"}, {"type": "uri", "value": "https://list.worldfloraonline.org/wfo-0000547831-2025-12"}, {"type": "uri", "value": "https://list.worldfloraonline.org/wfo-0000547832-2025-12"}, {"type": "uri", "value": "https://list.worldfloraonline.org/wfo-0001425446-2025-12"}, {"type": "uri", "value": "https://list.worldfloraonline.org/wfo-0000547838-2025-12"}, {"type": "uri", "value": "https://list.worldfloraonline.org/wfo-0000547841-2025-12"}, {"type": "uri", "value": "https://list.worldfloraonline.org/wfo-0000547842-2025-12"}, {"type": "uri", "value": "https://list.worldfloraonline.org/wfo-0000547843-2025-12"}, {"type": "uri", "value": "https://list.worldfloraonline.org/wfo-1000061295-2025-12"}, {"type": "uri", "value": "https://list.worldfloraonline.org/wfo-0000547846-2025-12"}, {"type": "uri", "value": "https://list.worldfloraonline.org/wfo-0000547848-2025-12"}, {"type": "uri", "value": "https://list.worldfloraonline.org/wfo-0001318315-2025-12"}, {"type": "uri", "value": "https://list.worldfloraonline.org/wfo-0000547849-2025-12"}, {"type": "uri", "value": "https://list.worldfloraonline.org/wfo-0000547851-2025-12"}, {"type": "uri", "value": "https://list.worldfloraonline.org/wfo-0000547853-2025-12"}, {"type": "uri", "value": "https://list.worldfloraonline.org/wfo-0000547854-2025-12"}, {"type": "uri", "value": "https://list.worldfloraonline.org/wfo-0000547856-2025-12"}, {"type": "uri", "value": "https://list.worldfloraonline.org/wfo-1000044372-2025-12"}, {"type": "uri", "value": "https://list.worldfloraonline.org/wfo-1000061282-2025-12"}, {"type": "uri", "value": "https://list.worldfloraonline.org/wfo-0000547857-2025-12"}, {"type": "uri", "value": "https://list.worldfloraonline.org/wfo-0000547858-2025-12"}, {"type": "uri", "value": "https://list.worldfloraonline.org/wfo-0000547859-2025-12"}, {"type": "uri", "value": "https://list.worldfloraonline.org/wfo-0001340241-2025-12"}, {"type": "uri", "value": "https://list.worldfloraonline.org/wfo-0001334685-2025-12"}, {"type": "uri", "value": "https://list.worldfloraonline.org/wfo-0000547860-2025-12"}, {"type": "uri", "value": "https://list.worldfloraonline.org/wfo-0000547861-2025-12"}, {"type": "uri", "value": "https://list.worldfloraonline.org/wfo-0000506402-2025-12"}, {"type": "uri", "value": "https://list.worldfloraonline.org/wfo-0000547862-2025-12"}, {"type": "uri", "value": "https://list.worldfloraonline.org/wfo-0000547872-2025-12"}, {"type": "uri", "value": "https://list.worldfloraonline.org/wfo-0000547873-2025-12"}, {"type": "uri", "value": "https://list.worldfloraonline.org/wfo-0000547874-2025-12"}, {"type": "uri", "value": "https://list.worldfloraonline.org/wfo-0000547875-2025-12"}, {"type": "uri", "value": "https://list.worldfloraonline.org/wfo-0000547876-2025-12"}, {"type": "uri", "value": "https://list.worldfloraonline.org/wfo-0000547879-2025-12"}, {"type": "uri", "value": "https://list.worldfloraonline.org/wfo-0000547883-2025-12"}, {"type": "uri", "value": "https://list.worldfloraonline.org/wfo-0000547885-2025-12"}, {"type": "uri", "value": "https://list.worldfloraonline.org/wfo-0000547886-2025-12"}, {"type": "uri", "value": "https://list.worldfloraonline.org/wfo-0000741670-2025-12"}, {"type": "uri", "value": "https://list.worldfloraonline.org/wfo-0000547888-2025-12"}, {"type": "uri", "value": "https://list.worldfloraonline.org/wfo-0000547889-2025-12"}, {"type": "uri", "value": "https://list.worldfloraonline.org/wfo-1000057803-2025-12"}, {"type": "uri", "value": "https://list.worldfloraonline.org/wfo-0000547891-2025-12"}, {"type": "uri", "value": "https://list.worldfloraonline.org/wfo-0001338150-2025-12"}, {"type": "uri", "value": "https://list.worldfloraonline.org/wfo-0000547892-2025-12"}, {"type": "uri", "value": "https://list.worldfloraonline.org/wfo-0000547893-2025-12"}, {"type": "uri", "value": "https://list.worldfloraonline.org/wfo-0000547894-2025-12"}, {"type": "uri", "value": "https://list.worldfloraonline.org/wfo-1000061297-2025-12"}, {"type": "uri", "value": "https://list.worldfloraonline.org/wfo-0000547900-2025-12"}, {"type": "uri", "value": "https://list.worldfloraonline.org/wfo-0000547901-2025-12"}, {"type": "uri", "value": "https://list.worldfloraonline.org/wfo-0000547902-2025-12"}, {"type": "uri", "value": "https://list.worldfloraonline.org/wfo-0000547904-2025-12"}, {"type": "uri", "value": "https://list.worldfloraonline.org/wfo-0000547905-2025-12"}, {"type": "uri", "value": "https://list.worldfloraonline.org/wfo-0000547906-2025-12"}, {"type": "uri", "value": "https://list.worldfloraonline.org/wfo-0000547907-2025-12"}, {"type": "uri", "value": "https://list.worldfloraonline.org/wfo-0000547908-2025-12"}, {"type": "uri", "value": "https://list.worldfloraonline.org/wfo-0000547912-2025-12"}, {"type": "uri", "value": "https://list.worldfloraonline.org/wfo-0001318316-2025-12"}, {"type": "uri", "value": "https://list.worldfloraonline.org/wfo-1000061296-2025-12"}, {"type": "uri", "value": "https://list.worldfloraonline.org/wfo-0000547916-2025-12"}, {"type": "uri", "value": "https://list.worldfloraonline.org/wfo-0000547918-2025-12"}, {"type": "uri", "value": "https://list.worldfloraonline.org/wfo-0000547919-2025-12"}, {"type": "uri", "value": "https://list.worldfloraonline.org/wfo-0000748776-2025-12"}, {"type": "uri", "value": "https://list.worldfloraonline.org/wfo-0000547923-2025-12"}, {"type": "uri", "value": "https://list.worldfloraonline.org/wfo-1000025522-2025-12"}, {"type": "uri", "value": "https://list.worldfloraonline.org/wfo-0000547928-2025-12"}, {"type": "uri", "value": "https://list.worldfloraonline.org/wfo-0000547941-2025-12"}, {"type": "uri", "value": "https://list.worldfloraonline.org/wfo-1000020491-2025-12"}, {"type": "uri", "value": "https://list.worldfloraonline.org/wfo-0001339848-2025-12"}, {"type": "uri", "value": "https://list.worldfloraonline.org/wfo-1000061289-2025-12"}, {"type": "uri", "value": "https://list.worldfloraonline.org/wfo-0000547944-2025-12"}, {"type": "uri", "value": "https://list.worldfloraonline.org/wfo-0000547946-2025-12"}, {"type": "uri", "value": "https://list.worldfloraonline.org/wfo-0000547947-2025-12"}, {"type": "uri", "value": "https://list.worldfloraonline.org/wfo-0000506403-2025-12"}, {"type": "uri", "value": "https://list.worldfloraonline.org/wfo-0000547949-2025-12"}, {"type": "uri", "value": "https://list.worldfloraonline.org/wfo-0000547950-2025-12"}, {"type": "uri", "value": "https://list.worldfloraonline.org/wfo-0000547951-2025-12"}, {"type": "uri", "value": "https://list.worldfloraonline.org/wfo-0000547952-2025-12"}, {"type": "uri", "value": "https://list.worldfloraonline.org/wfo-0000547954-2025-12"}, {"type": "uri", "value": "https://list.worldfloraonline.org/wfo-0000547955-2025-12"}, {"type": "uri", "value": "https://list.worldfloraonline.org/wfo-0000547957-2025-12"}, {"type": "uri", "value": "https://list.worldfloraonline.org/wfo-0001425506-2025-12"}, {"type": "uri", "value": "https://list.worldfloraonline.org/wfo-0000547959-2025-12"}, {"type": "uri", "value": "https://list.worldfloraonline.org/wfo-1000047012-2025-12"}, {"type": "uri", "value": "https://list.worldfloraonline.org/wfo-0000547960-2025-12"}, {"type": "uri", "value": "https://list.worldfloraonline.org/wfo-0000547961-2025-12"}, {"type": "uri", "value": "https://list.worldfloraonline.org/wfo-0000748781-2025-12"}, {"type": "uri", "value": "https://list.worldfloraonline.org/wfo-0000547966-2025-12"}, {"type": "uri", "value": "https://list.worldfloraonline.org/wfo-0000547967-2025-12"}, {"type": "uri", "value": "https://list.worldfloraonline.org/wfo-0000547968-2025-12"}, {"type": "uri", "value": "https://list.worldfloraonline.org/wfo-0000547969-2025-12"}, {"type": "uri", "value": "https://list.worldfloraonline.org/wfo-0000547970-2025-12"}, {"type": "uri", "value": "https://list.worldfloraonline.org/wfo-0000547971-2025-12"}, {"type": "uri", "value": "https://list.worldfloraonline.org/wfo-0000547972-2025-12"}, {"type": "uri", "value": "https://list.worldfloraonline.org/wfo-0000547973-2025-12"}, {"type": "uri", "value": "https://list.worldfloraonline.org/wfo-0000547977-2025-12"}, {"type": "uri", "value": "https://list.worldfloraonline.org/wfo-0000547978-2025-12"}, {"type": "uri", "value": "https://list.worldfloraonline.org/wfo-0000547980-2025-12"}, {"type": "uri", "value": "https://list.worldfloraonline.org/wfo-0000547982-2025-12"}, {"type": "uri", "value": "https://list.worldfloraonline.org/wfo-0000547984-2025-12"}, {"type": "uri", "value": "https://list.worldfloraonline.org/wfo-0000547985-2025-12"}, {"type": "uri", "value": "https://list.worldfloraonline.org/wfo-0000547986-2025-12"}, {"type": "uri", "value": "https://list.worldfloraonline.org/wfo-0000547997-2025-12"}, {"type": "uri", "value": "https://list.worldfloraonline.org/wfo-0000548001-2025-12"}, {"type": "uri", "value": "https://list.worldfloraonline.org/wfo-0000548011-2025-12"}, {"type": "uri", "value": "https://list.worldfloraonline.org/wfo-1000025523-2025-12"}, {"type": "uri", "value": "https://list.worldfloraonline.org/wfo-0001342884-2025-12"}, {"type": "uri", "value": "https://list.worldfloraonline.org/wfo-1000020492-2025-12"}, {"type": "uri", "value": "https://list.worldfloraonline.org/wfo-0000548013-2025-12"}, {"type": "uri", "value": "https://list.worldfloraonline.org/wfo-0000548014-2025-12"}, {"type": "uri", "value": "https://list.worldfloraonline.org/wfo-0000548015-2025-12"}, {"type": "uri", "value": "https://list.worldfloraonline.org/wfo-1000025524-2025-12"}, {"type": "uri", "value": "https://list.worldfloraonline.org/wfo-0000548016-2025-12"}, {"type": "uri", "value": "https://list.worldfloraonline.org/wfo-0000548018-2025-12"}, {"type": "uri", "value": "https://list.worldfloraonline.org/wfo-0000548020-2025-12"}, {"type": "uri", "value": "https://list.worldfloraonline.org/wfo-0000548021-2025-12"}, {"type": "uri", "value": "https://list.worldfloraonline.org/wfo-0000548023-2025-12"}, {"type": "uri", "value": "https://list.worldfloraonline.org/wfo-0000548026-2025-12"}, {"type": "uri", "value": "https://list.worldfloraonline.org/wfo-0000548031-2025-12"}, {"type": "uri", "value": "https://list.worldfloraonline.org/wfo-0001092308-2025-12"}, {"type": "uri", "value": "https://list.worldfloraonline.org/wfo-0000548034-2025-12"}, {"type": "uri", "value": "https://list.worldfloraonline.org/wfo-0000548035-2025-12"}, {"type": "uri", "value": "https://list.worldfloraonline.org/wfo-0000506404-2025-12"}, {"type": "uri", "value": "https://list.worldfloraonline.org/wfo-0000548036-2025-12"}, {"type": "uri", "value": "https://list.worldfloraonline.org/wfo-0000548037-2025-12"}, {"type": "uri", "value": "https://list.worldfloraonline.org/wfo-0001339849-2025-12"}, {"type": "uri", "value": "https://list.worldfloraonline.org/wfo-0000548038-2025-12"}, {"type": "uri", "value": "https://list.worldfloraonline.org/wfo-0000548040-2025-12"}, {"type": "uri", "value": "https://list.worldfloraonline.org/wfo-0000548041-2025-12"}, {"type": "uri", "value": "https://list.worldfloraonline.org/wfo-1000020493-2025-12"}, {"type": "uri", "value": "https://list.worldfloraonline.org/wfo-0000548047-2025-12"}, {"type": "uri", "value": "https://list.worldfloraonline.org/wfo-0000548049-2025-12"}, {"type": "uri", "value": "https://list.worldfloraonline.org/wfo-0000548053-2025-12"}, {"type": "uri", "value": "https://list.worldfloraonline.org/wfo-0000548060-2025-12"}, {"type": "uri", "value": "https://list.worldfloraonline.org/wfo-0001429111-2025-12"}, {"type": "uri", "value": "https://list.worldfloraonline.org/wfo-1000003198-2025-12"}, {"type": "uri", "value": "https://list.worldfloraonline.org/wfo-0000548063-2025-12"}, {"type": "uri", "value": "https://list.worldfloraonline.org/wfo-0000548065-2025-12"}, {"type": "uri", "value": "https://list.worldfloraonline.org/wfo-0000548066-2025-12"}, {"type": "uri", "value": "https://list.worldfloraonline.org/wfo-0001339850-2025-12"}, {"type": "uri", "value": "https://list.worldfloraonline.org/wfo-0000506405-2025-12"}, {"type": "uri", "value": "https://list.worldfloraonline.org/wfo-0000548068-2025-12"}, {"type": "uri", "value": "https://list.worldfloraonline.org/wfo-0000548075-2025-12"}, {"type": "uri", "value": "https://list.worldfloraonline.org/wfo-0000548077-2025-12"}, {"type": "uri", "value": "https://list.worldfloraonline.org/wfo-0000548078-2025-12"}, {"type": "uri", "value": "https://list.worldfloraonline.org/wfo-0000548081-2025-12"}, {"type": "uri", "value": "https://list.worldfloraonline.org/wfo-0000548084-2025-12"}, {"type": "uri", "value": "https://list.worldfloraonline.org/wfo-0000548085-2025-12"}, {"type": "uri", "value": "https://list.worldfloraonline.org/wfo-0000548087-2025-12"}, {"type": "uri", "value": "https://list.worldfloraonline.org/wfo-0000548089-2025-12"}, {"type": "uri", "value": "https://list.worldfloraonline.org/wfo-0000548090-2025-12"}, {"type": "uri", "value": "https://list.worldfloraonline.org/wfo-0000548091-2025-12"}, {"type": "uri", "value": "https://list.worldfloraonline.org/wfo-0000548092-2025-12"}, {"type": "uri", "value": "https://list.worldfloraonline.org/wfo-0000548095-2025-12"}, {"type": "uri", "value": "https://list.worldfloraonline.org/wfo-0000548096-2025-12"}, {"type": "uri", "value": "https://list.worldfloraonline.org/wfo-0001336381-2025-12"}, {"type": "uri", "value": "https://list.worldfloraonline.org/wfo-0000548099-2025-12"}, {"type": "uri", "value": "https://list.worldfloraonline.org/wfo-0000548100-2025-12"}, {"type": "uri", "value": "https://list.worldfloraonline.org/wfo-1000061287-2025-12"}, {"type": "uri", "value": "https://list.worldfloraonline.org/wfo-0000548101-2025-12"}, {"type": "uri", "value": "https://list.worldfloraonline.org/wfo-0000548102-2025-12"}, {"type": "uri", "value": "https://list.worldfloraonline.org/wfo-0001423514-2025-12"}, {"type": "uri", "value": "https://list.worldfloraonline.org/wfo-0000548104-2025-12"}, {"type": "uri", "value": "https://list.worldfloraonline.org/wfo-0000548106-2025-12"}, {"type": "uri", "value": "https://list.worldfloraonline.org/wfo-0000548107-2025-12"}, {"type": "uri", "value": "https://list.worldfloraonline.org/wfo-1000061293-2025-12"}, {"type": "uri", "value": "https://list.worldfloraonline.org/wfo-0000548108-2025-12"}, {"type": "uri", "value": "https://list.worldfloraonline.org/wfo-0000548109-2025-12"}, {"type": "uri", "value": "https://list.worldfloraonline.org/wfo-0000548111-2025-12"}, {"type": "uri", "value": "https://list.worldfloraonline.org/wfo-0000548113-2025-12"}, {"type": "uri", "value": "https://list.worldfloraonline.org/wfo-1000003199-2025-12"}, {"type": "uri", "value": "https://list.worldfloraonline.org/wfo-0000548114-2025-12"}, {"type": "uri", "value": "https://list.worldfloraonline.org/wfo-0000548115-2025-12"}, {"type": "uri", "value": "https://list.worldfloraonline.org/wfo-0000548118-2025-12"}, {"type": "uri", "value": "https://list.worldfloraonline.org/wfo-0000548120-2025-12"}, {"type": "uri", "value": "https://list.worldfloraonline.org/wfo-0000548124-2025-12"}, {"type": "uri", "value": "https://list.worldfloraonline.org/wfo-0000548125-2025-12"}, {"type": "uri", "value": "https://list.worldfloraonline.org/wfo-0000548127-2025-12"}, {"type": "uri", "value": "https://list.worldfloraonline.org/wfo-0000548140-2025-12"}, {"type": "uri", "value": "https://list.worldfloraonline.org/wfo-0000548142-2025-12"}, {"type": "uri", "value": "https://list.worldfloraonline.org/wfo-0000548143-2025-12"}, {"type": "uri", "value": "https://list.worldfloraonline.org/wfo-0000548144-2025-12"}, {"type": "uri", "value": "https://list.worldfloraonline.org/wfo-0001339851-2025-12"}, {"type": "uri", "value": "https://list.worldfloraonline.org/wfo-1000025525-2025-12"}, {"type": "uri", "value": "https://list.worldfloraonline.org/wfo-0000548148-2025-12"}, {"type": "uri", "value": "https://list.worldfloraonline.org/wfo-0000548150-2025-12"}, {"type": "uri", "value": "https://list.worldfloraonline.org/wfo-0000548151-2025-12"}, {"type": "uri", "value": "https://list.worldfloraonline.org/wfo-0001345724-2025-12"}, {"type": "uri", "value": "https://list.worldfloraonline.org/wfo-0000548152-2025-12"}, {"type": "uri", "value": "https://list.worldfloraonline.org/wfo-1000057106-2025-12"}, {"type": "uri", "value": "https://list.worldfloraonline.org/wfo-0000548153-2025-12"}, {"type": "uri", "value": "https://list.worldfloraonline.org/wfo-0000548156-2025-12"}, {"type": "uri", "value": "https://list.worldfloraonline.org/wfo-0000548157-2025-12"}, {"type": "uri", "value": "https://list.worldfloraonline.org/wfo-0000548164-2025-12"}, {"type": "uri", "value": "https://list.worldfloraonline.org/wfo-0000548165-2025-12"}, {"type": "uri", "value": "https://list.worldfloraonline.org/wfo-0000548166-2025-12"}, {"type": "uri", "value": "https://list.worldfloraonline.org/wfo-0000548167-2025-12"}, {"type": "uri", "value": "https://list.worldfloraonline.org/wfo-0001339852-2025-12"}, {"type": "uri", "value": "https://list.worldfloraonline.org/wfo-0000548171-2025-12"}, {"type": "uri", "value": "https://list.worldfloraonline.org/wfo-0000548174-2025-12"}, {"type": "uri", "value": "https://list.worldfloraonline.org/wfo-0000548176-2025-12"}, {"type": "uri", "value": "https://list.worldfloraonline.org/wfo-0000548177-2025-12"}, {"type": "uri", "value": "https://list.worldfloraonline.org/wfo-0000548178-2025-12"}, {"type": "uri", "value": "https://list.worldfloraonline.org/wfo-0000548183-2025-12"}, {"type": "uri", "value": "https://list.worldfloraonline.org/wfo-0000548186-2025-12"}, {"type": "uri", "value": "https://list.worldfloraonline.org/wfo-0000548188-2025-12"}, {"type": "uri", "value": "https://list.worldfloraonline.org/wfo-0001339853-2025-12"}, {"type": "uri", "value": "https://list.worldfloraonline.org/wfo-0000548189-2025-12"}, {"type": "uri", "value": "https://list.worldfloraonline.org/wfo-0000506407-2025-12"}, {"type": "uri", "value": "https://list.worldfloraonline.org/wfo-0000548191-2025-12"}, {"type": "uri", "value": "https://list.worldfloraonline.org/wfo-0000548193-2025-12"}, {"type": "uri", "value": "https://list.worldfloraonline.org/wfo-0000548196-2025-12"}, {"type": "uri", "value": "https://list.worldfloraonline.org/wfo-0000548197-2025-12"}, {"type": "uri", "value": "https://list.worldfloraonline.org/wfo-0000548198-2025-12"}, {"type": "uri", "value": "https://list.worldfloraonline.org/wfo-0001345519-2025-12"}, {"type": "uri", "value": "https://list.worldfloraonline.org/wfo-0000548199-2025-12"}, {"type": "uri", "value": "https://list.worldfloraonline.org/wfo-0000548202-2025-12"}, {"type": "uri", "value": "https://list.worldfloraonline.org/wfo-0000548205-2025-12"}, {"type": "uri", "value": "https://list.worldfloraonline.org/wfo-1000003200-2025-12"}, {"type": "uri", "value": "https://list.worldfloraonline.org/wfo-0000548207-2025-12"}, {"type": "uri", "value": "https://list.worldfloraonline.org/wfo-0000548208-2025-12"}, {"type": "uri", "value": "https://list.worldfloraonline.org/wfo-0000548210-2025-12"}, {"type": "uri", "value": "https://list.worldfloraonline.org/wfo-0000548211-2025-12"}, {"type": "uri", "value": "https://list.worldfloraonline.org/wfo-0000548215-2025-12"}, {"type": "uri", "value": "https://list.worldfloraonline.org/wfo-0000548216-2025-12"}, {"type": "uri", "value": "https://list.worldfloraonline.org/wfo-0000548217-2025-12"}, {"type": "uri", "value": "https://list.worldfloraonline.org/wfo-0000548220-2025-12"}, {"type": "uri", "value": "https://list.worldfloraonline.org/wfo-0000506408-2025-12"}, {"type": "uri", "value": "https://list.worldfloraonline.org/wfo-0000548223-2025-12"}, {"type": "uri", "value": "https://list.worldfloraonline.org/wfo-1000044373-2025-12"}, {"type": "uri", "value": "https://list.worldfloraonline.org/wfo-0000548224-2025-12"}, {"type": "uri", "value": "https://list.worldfloraonline.org/wfo-0000548227-2025-12"}, {"type": "uri", "value": "https://list.worldfloraonline.org/wfo-0000548228-2025-12"}, {"type": "uri", "value": "https://list.worldfloraonline.org/wfo-0000548229-2025-12"}, {"type": "uri", "value": "https://list.worldfloraonline.org/wfo-0000548230-2025-12"}, {"type": "uri", "value": "https://list.worldfloraonline.org/wfo-1000003201-2025-12"}, {"type": "uri", "value": "https://list.worldfloraonline.org/wfo-0000548231-2025-12"}, {"type": "uri", "value": "https://list.worldfloraonline.org/wfo-1000020494-2025-12"}, {"type": "uri", "value": "https://list.worldfloraonline.org/wfo-0000548232-2025-12"}, {"type": "uri", "value": "https://list.worldfloraonline.org/wfo-0000548236-2025-12"}, {"type": "uri", "value": "https://list.worldfloraonline.org/wfo-0000548240-2025-12"}, {"type": "uri", "value": "https://list.worldfloraonline.org/wfo-0000548241-2025-12"}, {"type": "uri", "value": "https://list.worldfloraonline.org/wfo-0000548243-2025-12"}, {"type": "uri", "value": "https://list.worldfloraonline.org/wfo-1000035160-2025-12"}, {"type": "uri", "value": "https://list.worldfloraonline.org/wfo-0000548244-2025-12"}, {"type": "uri", "value": "https://list.worldfloraonline.org/wfo-0000548246-2025-12"}, {"type": "uri", "value": "https://list.worldfloraonline.org/wfo-1000040963-2025-12"}, {"type": "uri", "value": "https://list.worldfloraonline.org/wfo-0001337976-2025-12"}, {"type": "uri", "value": "https://list.worldfloraonline.org/wfo-0000548250-2025-12"}, {"type": "uri", "value": "https://list.worldfloraonline.org/wfo-1000025526-2025-12"}, {"type": "uri", "value": "https://list.worldfloraonline.org/wfo-0000548252-2025-12"}, {"type": "uri", "value": "https://list.worldfloraonline.org/wfo-1000035912-2025-12"}, {"type": "uri", "value": "https://list.worldfloraonline.org/wfo-1000040721-2025-12"}, {"type": "uri", "value": "https://list.worldfloraonline.org/wfo-0000548261-2025-12"}, {"type": "uri", "value": "https://list.worldfloraonline.org/wfo-0000548264-2025-12"}, {"type": "uri", "value": "https://list.worldfloraonline.org/wfo-0000548266-2025-12"}, {"type": "uri", "value": "https://list.worldfloraonline.org/wfo-0000548267-2025-12"}, {"type": "uri", "value": "https://list.worldfloraonline.org/wfo-0000548271-2025-12"}, {"type": "uri", "value": "https://list.worldfloraonline.org/wfo-0000548273-2025-12"}, {"type": "uri", "value": "https://list.worldfloraonline.org/wfo-0000548276-2025-12"}, {"type": "uri", "value": "https://list.worldfloraonline.org/wfo-0000548277-2025-12"}, {"type": "uri", "value": "https://list.worldfloraonline.org/wfo-0000548284-2025-12"}, {"type": "uri", "value": "https://list.worldfloraonline.org/wfo-0000548285-2025-12"}, {"type": "uri", "value": "https://list.worldfloraonline.org/wfo-0000548286-2025-12"}, {"type": "uri", "value": "https://list.worldfloraonline.org/wfo-0000548291-2025-12"}, {"type": "uri", "value": "https://list.worldfloraonline.org/wfo-0001340177-2025-12"}, {"type": "uri", "value": "https://list.worldfloraonline.org/wfo-0000548292-2025-12"}, {"type": "uri", "value": "https://list.worldfloraonline.org/wfo-0000548296-2025-12"}, {"type": "uri", "value": "https://list.worldfloraonline.org/wfo-0000548297-2025-12"}, {"type": "uri", "value": "https://list.worldfloraonline.org/wfo-0001265437-2025-12"}, {"type": "uri", "value": "https://list.worldfloraonline.org/wfo-0000548298-2025-12"}, {"type": "uri", "value": "https://list.worldfloraonline.org/wfo-0001345725-2025-12"}, {"type": "uri", "value": "https://list.worldfloraonline.org/wfo-0000548306-2025-12"}, {"type": "uri", "value": "https://list.worldfloraonline.org/wfo-0000548307-2025-12"}, {"type": "uri", "value": "https://list.worldfloraonline.org/wfo-0000548308-2025-12"}, {"type": "uri", "value": "https://list.worldfloraonline.org/wfo-0000548309-2025-12"}, {"type": "uri", "value": "https://list.worldfloraonline.org/wfo-0000548310-2025-12"}, {"type": "uri", "value": "https://list.worldfloraonline.org/wfo-0000548313-2025-12"}, {"type": "uri", "value": "https://list.worldfloraonline.org/wfo-0000548314-2025-12"}, {"type": "uri", "value": "https://list.worldfloraonline.org/wfo-0000548315-2025-12"}, {"type": "uri", "value": "https://list.worldfloraonline.org/wfo-0000548317-2025-12"}, {"type": "uri", "value": "https://list.worldfloraonline.org/wfo-0000548318-2025-12"}, {"type": "uri", "value": "https://list.worldfloraonline.org/wfo-0000548321-2025-12"}, {"type": "uri", "value": "https://list.worldfloraonline.org/wfo-0000548326-2025-12"}, {"type": "uri", "value": "https://list.worldfloraonline.org/wfo-0001339854-2025-12"}, {"type": "uri", "value": "https://list.worldfloraonline.org/wfo-0000548327-2025-12"}, {"type": "uri", "value": "https://list.worldfloraonline.org/wfo-0000548329-2025-12"}, {"type": "uri", "value": "https://list.worldfloraonline.org/wfo-0000548336-2025-12"}, {"type": "uri", "value": "https://list.worldfloraonline.org/wfo-0000548340-2025-12"}, {"type": "uri", "value": "https://list.worldfloraonline.org/wfo-0000548341-2025-12"}, {"type": "uri", "value": "https://list.worldfloraonline.org/wfo-0000548343-2025-12"}, {"type": "uri", "value": "https://list.worldfloraonline.org/wfo-0000548344-2025-12"}, {"type": "uri", "value": "https://list.worldfloraonline.org/wfo-0000548346-2025-12"}, {"type": "uri", "value": "https://list.worldfloraonline.org/wfo-0000548348-2025-12"}, {"type": "uri", "value": "https://list.worldfloraonline.org/wfo-0001330901-2025-12"}, {"type": "uri", "value": "https://list.worldfloraonline.org/wfo-0000548350-2025-12"}, {"type": "uri", "value": "https://list.worldfloraonline.org/wfo-0000548351-2025-12"}, {"type": "uri", "value": "https://list.worldfloraonline.org/wfo-0001339855-2025-12"}, {"type": "uri", "value": "https://list.worldfloraonline.org/wfo-0000548357-2025-12"}, {"type": "uri", "value": "https://list.worldfloraonline.org/wfo-0000548359-2025-12"}, {"type": "uri", "value": "https://list.worldfloraonline.org/wfo-0000548361-2025-12"}, {"type": "uri", "value": "https://list.worldfloraonline.org/wfo-0000548362-2025-12"}, {"type": "uri", "value": "https://list.worldfloraonline.org/wfo-1000057801-2025-12"}, {"type": "uri", "value": "https://list.worldfloraonline.org/wfo-0000548363-2025-12"}, {"type": "uri", "value": "https://list.worldfloraonline.org/wfo-0000548364-2025-12"}, {"type": "uri", "value": "https://list.worldfloraonline.org/wfo-0000548365-2025-12"}, {"type": "uri", "value": "https://list.worldfloraonline.org/wfo-0000548368-2025-12"}, {"type": "uri", "value": "https://list.worldfloraonline.org/wfo-0000548370-2025-12"}, {"type": "uri", "value": "https://list.worldfloraonline.org/wfo-0001318318-2025-12"}, {"type": "uri", "value": "https://list.worldfloraonline.org/wfo-0000548375-2025-12"}, {"type": "uri", "value": "https://list.worldfloraonline.org/wfo-1000061290-2025-12"}, {"type": "uri", "value": "https://list.worldfloraonline.org/wfo-0000548382-2025-12"}, {"type": "uri", "value": "https://list.worldfloraonline.org/wfo-0000548383-2025-12"}, {"type": "uri", "value": "https://list.worldfloraonline.org/wfo-0001340402-2025-12"}, {"type": "uri", "value": "https://list.worldfloraonline.org/wfo-0001286115-2025-12"}, {"type": "uri", "value": "https://list.worldfloraonline.org/wfo-0000548387-2025-12"}, {"type": "uri", "value": "https://list.worldfloraonline.org/wfo-0000548391-2025-12"}, {"type": "uri", "value": "https://list.worldfloraonline.org/wfo-0000548392-2025-12"}, {"type": "uri", "value": "https://list.worldfloraonline.org/wfo-0000548395-2025-12"}, {"type": "uri", "value": "https://list.worldfloraonline.org/wfo-1000029495-2025-12"}, {"type": "uri", "value": "https://list.worldfloraonline.org/wfo-0000548396-2025-12"}, {"type": "uri", "value": "https://list.worldfloraonline.org/wfo-0000548398-2025-12"}, {"type": "uri", "value": "https://list.worldfloraonline.org/wfo-0000548401-2025-12"}, {"type": "uri", "value": "https://list.worldfloraonline.org/wfo-0001339856-2025-12"}, {"type": "uri", "value": "https://list.worldfloraonline.org/wfo-0000548403-2025-12"}, {"type": "uri", "value": "https://list.worldfloraonline.org/wfo-0000548404-2025-12"}, {"type": "uri", "value": "https://list.worldfloraonline.org/wfo-1000003202-2025-12"}, {"type": "uri", "value": "https://list.worldfloraonline.org/wfo-1000061292-2025-12"}, {"type": "uri", "value": "https://list.worldfloraonline.org/wfo-0000548409-2025-12"}, {"type": "uri", "value": "https://list.worldfloraonline.org/wfo-0000548410-2025-12"}, {"type": "uri", "value": "https://list.worldfloraonline.org/wfo-0000548412-2025-12"}, {"type": "uri", "value": "https://list.worldfloraonline.org/wfo-0000548413-2025-12"}, {"type": "uri", "value": "https://list.worldfloraonline.org/wfo-0000548414-2025-12"}, {"type": "uri", "value": "https://list.worldfloraonline.org/wfo-0000548415-2025-12"}, {"type": "uri", "value": "https://list.worldfloraonline.org/wfo-0000548420-2025-12"}, {"type": "uri", "value": "https://list.worldfloraonline.org/wfo-0000548421-2025-12"}, {"type": "uri", "value": "https://list.worldfloraonline.org/wfo-0000548425-2025-12"}, {"type": "uri", "value": "https://list.worldfloraonline.org/wfo-0000548431-2025-12"}, {"type": "uri", "value": "https://list.worldfloraonline.org/wfo-0000548432-2025-12"}, {"type": "uri", "value": "https://list.worldfloraonline.org/wfo-0000548435-2025-12"}, {"type": "uri", "value": "https://list.worldfloraonline.org/wfo-0000548436-2025-12"}, {"type": "uri", "value": "https://list.worldfloraonline.org/wfo-1000061288-2025-12"}, {"type": "uri", "value": "https://list.worldfloraonline.org/wfo-0000548438-2025-12"}, {"type": "uri", "value": "https://list.worldfloraonline.org/wfo-0000548439-2025-12"}, {"type": "uri", "value": "https://list.worldfloraonline.org/wfo-0000548443-2025-12"}, {"type": "uri", "value": "https://list.worldfloraonline.org/wfo-0000548447-2025-12"}, {"type": "uri", "value": "https://list.worldfloraonline.org/wfo-0000548449-2025-12"}, {"type": "uri", "value": "https://list.worldfloraonline.org/wfo-0001333636-2025-12"}, {"type": "uri", "value": "https://list.worldfloraonline.org/wfo-0000548451-2025-12"}, {"type": "uri", "value": "https://list.worldfloraonline.org/wfo-0000548453-2025-12"}, {"type": "uri", "value": "https://list.worldfloraonline.org/wfo-0000548455-2025-12"}, {"type": "uri", "value": "https://list.worldfloraonline.org/wfo-0000548456-2025-12"}, {"type": "uri", "value": "https://list.worldfloraonline.org/wfo-1000025527-2025-12"}, {"type": "uri", "value": "https://list.worldfloraonline.org/wfo-0000548458-2025-12"}, {"type": "uri", "value": "https://list.worldfloraonline.org/wfo-0000548460-2025-12"}, {"type": "uri", "value": "https://list.worldfloraonline.org/wfo-1000025528-2025-12"}, {"type": "uri", "value": "https://list.worldfloraonline.org/wfo-1000021108-2025-12"}, {"type": "uri", "value": "https://list.worldfloraonline.org/wfo-0000548462-2025-12"}, {"type": "uri", "value": "https://list.worldfloraonline.org/wfo-0000548463-2025-12"}, {"type": "uri", "value": "https://list.worldfloraonline.org/wfo-0000548465-2025-12"}, {"type": "uri", "value": "https://list.worldfloraonline.org/wfo-0000548466-2025-12"}, {"type": "uri", "value": "https://list.worldfloraonline.org/wfo-0000548467-2025-12"}, {"type": "uri", "value": "https://list.worldfloraonline.org/wfo-1000061283-2025-12"}, {"type": "uri", "value": "https://list.worldfloraonline.org/wfo-0000548471-2025-12"}, {"type": "uri", "value": "https://list.worldfloraonline.org/wfo-1000021109-2025-12"}, {"type": "uri", "value": "https://list.worldfloraonline.org/wfo-0000548472-2025-12"}, {"type": "uri", "value": "https://list.worldfloraonline.org/wfo-0000548473-2025-12"}, {"type": "uri", "value": "https://list.worldfloraonline.org/wfo-0000548474-2025-12"}, {"type": "uri", "value": "https://list.worldfloraonline.org/wfo-0000548475-2025-12"}, {"type": "uri", "value": "https://list.worldfloraonline.org/wfo-0000548477-2025-12"}, {"type": "uri", "value": "https://list.worldfloraonline.org/wfo-0000745653-2025-12"}, {"type": "uri", "value": "https://list.worldfloraonline.org/wfo-0000548480-2025-12"}, {"type": "uri", "value": "https://list.worldfloraonline.org/wfo-0001341181-2025-12"}, {"type": "uri", "value": "https://list.worldfloraonline.org/wfo-1000021110-2025-12"}, {"type": "uri", "value": "https://list.worldfloraonline.org/wfo-0000506409-2025-12"}, {"type": "uri", "value": "https://list.worldfloraonline.org/wfo-1000020495-2025-12"}, {"type": "uri", "value": "https://list.worldfloraonline.org/wfo-1000035264-2025-12"}, {"type": "uri", "value": "https://list.worldfloraonline.org/wfo-0000548481-2025-12"}, {"type": "uri", "value": "https://list.worldfloraonline.org/wfo-0000548482-2025-12"}, {"type": "uri", "value": "https://list.worldfloraonline.org/wfo-0001318319-2025-12"}, {"type": "uri", "value": "https://list.worldfloraonline.org/wfo-0000548483-2025-12"}, {"type": "uri", "value": "https://list.worldfloraonline.org/wfo-0000548484-2025-12"}, {"type": "uri", "value": "https://list.worldfloraonline.org/wfo-0000548485-2025-12"}], "http://purl.org/dc/terms/hasSynonym": [{"type": "uri", "value": "https://list.worldfloraonline.org/wfo-1200093870"}, {"type": "uri", "value": "https://list.worldfloraonline.org/wfo-4000001567"}, {"type": "uri", "value": "https://list.worldfloraonline.org/wfo-4000010835"}, {"type": "uri", "value": "https://list.worldfloraonline.org/wfo-4000011562"}, {"type": "uri", "value": "https://list.worldfloraonline.org/wfo-4000011705"}, {"type": "uri", "value": "https://list.worldfloraonline.org/wfo-4000012692"}, {"type": "uri", "value": "https://list.worldfloraonline.org/wfo-4000013078"}, {"type": "uri", "value": "https://list.worldfloraonline.org/wfo-4000013397"}, {"type": "uri", "value": "https://list.worldfloraonline.org/wfo-4000016286"}, {"type": "uri", "value": "https://list.worldfloraonline.org/wfo-4000017833"}, {"type": "uri", "value": "https://list.worldfloraonline.org/wfo-4000018016"}, {"type": "uri", "value": "https://list.worldfloraonline.org/wfo-4000019247"}, {"type": "uri", "value": "https://list.worldfloraonline.org/wfo-4000019346"}, {"type": "uri", "value": "https://list.worldfloraonline.org/wfo-4000028138"}, {"type": "uri", "value": "https://list.worldfloraonline.org/wfo-4000029893"}, {"type": "uri", "value": "https://list.worldfloraonline.org/wfo-4000030020"}, {"type": "uri", "value": "https://list.worldfloraonline.org/wfo-4000031818"}, {"type": "uri", "value": "https://list.worldfloraonline.org/wfo-4000031903"}, {"type": "uri", "value": "https://list.worldfloraonline.org/wfo-4000035496"}, {"type": "uri", "value": "https://list.worldfloraonline.org/wfo-4000039464"}, {"type": "uri", "value": "https://list.worldfloraonline.org/wfo-4000044863"}, {"type": "uri", "value": "https://list.worldfloraonline.org/wfo-4000044864"}], "http://purl.org/dc/terms/references": [{"type": "uri", "value": "https://powo.science.kew.org/taxon/urn:lsid:ipni.org:names:330834-2"}]}, "https://list.worldfloraonline.org/wfo-4000003062": {"http://www.w3.org/1999/02/22-rdf-syntax-ns#type": [{"type": "uri", "value": "https://list.worldfloraonline.org/terms/TaxonName"}], "https://list.worldfloraonline.org/terms/rank": [{"type": "uri", "value": "https://list.worldfloraonline.org/terms/genus"}], "https://list.worldfloraonline.org/terms/fullName": [{"type": "literal", "value": "Aristolochia L."}], "https://list.worldfloraonline.org/terms/authorship": [{"type": "literal", "value": "L."}], "http://purl.org/dc/terms/creator": [{"type": "literal", "value": "L."}], "https://list.worldfloraonline.org/terms/publicationCitation": [{"type": "literal", "value": "Sp. Pl. : 960 (1753)"}], "https://list.worldfloraonline.org/terms/acceptedNameFor": [{"type": "uri", "value": "https://list.worldfloraonline.org/wfo-4000003062-2018-07"}, {"type": "uri", "value": "https://list.worldfloraonline.org/wfo-4000003062-2019-03"}, {"type": "uri", "value": "https://list.worldfloraonline.org/wfo-4000003062-2019-05"}, {"type": "uri", "value": "https://list.worldfloraonline.org/wfo-4000003062-2021-12"}, {"type": "uri", "value": "https://list.worldfloraonline.org/wfo-4000003062-2022-06"}, {"type": "uri", "value": "https://list.worldfloraonline.org/wfo-4000003062-2022-12"}, {"type": "uri", "value": "https://list.worldfloraonline.org/wfo-4000003062-2023-06"}, {"type": "uri", "value": "https://list.worldfloraonline.org/wfo-4000003062-2023-12"}, {"type": "uri", "value": "https://list.worldfloraonline.org/wfo-4000003062-2024-06"}, {"type": "uri", "value": "https://list.worldfloraonline.org/wfo-4000003062-2024-12"}, {"type": "uri", "value": "https://list.worldfloraonline.org/wfo-4000003062-2025-06"}, {"type": "uri", "value": "https://list.worldfloraonline.org/wfo-4000003062-2025-12"}], "https://list.worldfloraonline.org/terms/currentPreferredUsage": [{"type": "uri", "value": "https://list.worldfloraonline.org/wfo-4000003062-2025-12"}], "https://list.worldfloraonline.org/terms/deduplicatedID": [{"type": "literal", "value": "wfo-4000003061"}], "http://purl.org/dc/terms/references": [{"type": "uri", "value": "https://www.biodiversitylibrary.org/page/358981"}, {"type": "uri", "value": "http://www.wikidata.org/entity/Q39503"}, {"type": "uri", "value": "http://www.wikidata.org/entity/Q1043"}, {"type": "uri", "value": "https://www.ipni.org/n/330834-2"}, {"type": "uri", "value": "http://www.theplantlist.org/browse/A/Aristolochiaceae/Aristolochia/"}, {"type": "uri", "value": "http://www.theplantlist.org/1.1/browse/A/Aristolochiaceae/Aristolochia/"}]}, "https://www.biodiversitylibrary.org/page/358981": {"http://purl.org/dc/terms/title": [{"type": "literal", "value": "Sp. Pl. 2: 960. 1753 [1 May 1753] "}], "http://purl.org/dc/terms/type": [{"type": "literal", "value": "literature"}], "http://purl.org/dc/terms/description": [{"type": "literal", "value": "BHL link from IPNI metadata."}], "http://ogp.me/ns#image": [{"type": "uri", "value": "https://www.biodiversitylibrary.org/pagethumb/358981"}]}, "http://www.wikidata.org/entity/Q39503": {"http://purl.org/dc/terms/title": [{"type": "literal", "value": "Artemis"}], "http://purl.org/dc/terms/type": [{"type": "literal", "value": "person"}], "http://purl.org/dc/terms/description": [{"type": "literal", "value": "Named for Artemis - Greek goddess. [Source 10.3897/BDJ.11.e114408]"}], "http://ogp.me/ns#image": [{"type": "uri", "value": "https://upload.wikimedia.org/wikipedia/commons/thumb/b/b7/Diana_of_Versailles.jpg/200px-Diana_of_Versailles.jpg"}]}, "http://www.wikidata.org/entity/Q1043": {"http://purl.org/dc/terms/title": [{"type": "literal", "value": "Carl Linnaeus (1707-1778)"}], "http://purl.org/dc/terms/type": [{"type": "literal", "value": "person"}], "http://purl.org/dc/terms/description": [{"type": "literal", "value": "Based on occurrence of standard abbreviation 'L.' in the authors string."}], "http://ogp.me/ns#image": [{"type": "uri", "value": "https://upload.wikimedia.org/wikipedia/commons/thumb/6/68/Carl_von_Linn%C3%A9.jpg/200px-Carl_von_Linn.jpg"}]}, "https://www.ipni.org/n/330834-2": {"http://purl.org/dc/terms/title": [{"type": "literal", "value": "IPNI record: 330834-2"}], "http://purl.org/dc/terms/type": [{"type": "literal", "value": "database"}]}, "http://www.theplantlist.org/browse/A/Aristolochiaceae/Aristolochia/": {"http://purl.org/dc/terms/title": [{"type": "literal", "value": "The Plant List version 1.0, record: Aristolochiaceae Aristolochia"}], "http://purl.org/dc/terms/type": [{"type": "literal", "value": "database"}]}, "http://www.theplantlist.org/1.1/browse/A/Aristolochiaceae/Aristolochia/": {"http://purl.org/dc/terms/title": [{"type": "literal", "value": "The Plant List version 1.1, record: Aristolochiaceae Aristolochia"}], "http://purl.org/dc/terms/type": [{"type": "literal", "value": "database"}]}, "https://powo.science.kew.org/taxon/urn:lsid:ipni.org:names:330834-2": {"http://purl.org/dc/terms/title": [{"type": "literal", "value": "POWO record for urn:lsid:ipni.org:names:330834-2"}], "http://purl.org/dc/terms/type": [{"type": "literal", "value": "database"}], "http://purl.org/dc/terms/description": [{"type": "literal", "value": "Govaerts R (ed.). 2024. WCVP: World Checklist of Vascular Plants. Facilitated by the Royal Botanic Gardens, Kew. [WWW document] URL http://sftp.kew.org/pub/data-repositories/WCVP/ [accessed 21 May 2024]."}]}}